{
  "_class": "shapePath",
  "booleanOperation": -1,
  "do_objectID": "5450A2AD-3B82-48FA-B0D8-3C0E70D12D27",
  "edited": true,
  "exportOptions": {
    "_class": "exportOptions",
    "do_objectID": "18C63291-B558-463B-8EE2-8B58B6BC2804",
    "exportFormats": [
    ],
    "includedLayerIds": [
    ],
    "layerOptions": 0,
    "shouldTrim": false
  },
  "frame": {
    "_class": "rect",
    "constrainProportions": false,
    "do_objectID": "80695F35-4872-432C-82FF-84DD099D7CF7",
    "height": 6,
    "width": 6,
    "x": 12,
    "y": 0
  },
  "isClosed": true,
  "isFixedToViewport": false,
  "isFlippedHorizontal": false,
  "isFlippedVertical": false,
  "isLocked": false,
  "isVisible": true,
  "layerListExpandedType": 0,
  "name": "Path",
  "nameIsFixed": false,
  "pointRadiusBehaviour": 1,
  "points": [
    {
      "_class": "curvePoint",
      "cornerRadius": 0,
      "curveFrom": "{0, 1}",
      "curveMode": 1,
      "curveTo": "{0, 1}",
      "hasCurveFrom": false,
      "hasCurveTo": false,
      "point": "{0, 1}"
    },
    {
      "_class": "curvePoint",
      "cornerRadius": 0,
      "curveFrom": "{0.33333333333333331, 1}",
      "curveMode": 1,
      "curveTo": "{0.33333333333333331, 1}",
      "hasCurveFrom": false,
      "hasCurveTo": false,
      "point": "{0.33333333333333331, 1}"
    },
    {
      "_class": "curvePoint",
      "cornerRadius": 0,
      "curveFrom": "{0.33333333333333331, 0.66666666666666663}",
      "curveMode": 1,
      "curveTo": "{0.33333333333333331, 0.66666666666666663}",
      "hasCurveFrom": false,
      "hasCurveTo": false,
      "point": "{0.33333333333333331, 0.66666666666666663}"
    },
    {
      "_class": "curvePoint",
      "cornerRadius": 0,
      "curveFrom": "{1, 0.66666666666666663}",
      "curveMode": 1,
      "curveTo": "{1, 0.66666666666666663}",
      "hasCurveFrom": false,
      "hasCurveTo": false,
      "point": "{1, 0.66666666666666663}"
    },
    {
      "_class": "curvePoint",
      "cornerRadius": 0,
      "curveFrom": "{1, 0.33333333333333331}",
      "curveMode": 1,
      "curveTo": "{1, 0.33333333333333331}",
      "hasCurveFrom": false,
      "hasCurveTo": false,
      "point": "{1, 0.33333333333333331}"
    },
    {
      "_class": "curvePoint",
      "cornerRadius": 0,
      "curveFrom": "{0.33333333333333331, 0.33333333333333331}",
      "curveMode": 1,
      "curveTo": "{0.33333333333333331, 0.33333333333333331}",
      "hasCurveFrom": false,
      "hasCurveTo": false,
      "point": "{0.33333333333333331, 0.33333333333333331}"
    },
    {
      "_class": "curvePoint",
      "cornerRadius": 0,
      "curveFrom": "{0.33333333333333331, 0}",
      "curveMode": 1,
      "curveTo": "{0.33333333333333331, 0}",
      "hasCurveFrom": false,
      "hasCurveTo": false,
      "point": "{0.33333333333333331, 0}"
    },
    {
      "_class": "curvePoint",
      "cornerRadius": 0,
      "curveFrom": "{0, 0}",
      "curveMode": 1,
      "curveTo": "{0, 0}",
      "hasCurveFrom": false,
      "hasCurveTo": false,
      "point": "{0, 0}"
    }
  ],
  "resizingConstraint": 63,
  "resizingType": 0,
  "rotation": 0,
  "shouldBreakMaskChain": false
}