{
  "_class": "symbolInstance",
  "booleanOperation": 0,
  "do_objectID": "B7C23289-044C-4125-BA83-4ED2592D6703",
  "exportOptions": {
    "_class": "exportOptions",
    "do_objectID": "BE8C8FB7-5A21-4F6A-8E7A-3CF343AF1009",
    "exportFormats": [
    ],
    "includedLayerIds": [
    ],
    "layerOptions": 0,
    "shouldTrim": false
  },
  "frame": {
    "_class": "rect",
    "constrainProportions": false,
    "do_objectID": "DDCABD8A-564F-4E12-9DDC-BDDB2FFE4E08",
    "height": 2,
    "width": 2,
    "x": 28,
    "y": 0
  },
  "horizontalSpacing": 0,
  "isFixedToViewport": false,
  "isFlippedHorizontal": false,
  "isFlippedVertical": false,
  "isLocked": false,
  "isVisible": true,
  "layerListExpandedType": 0,
  "name": "Tick 2",
  "nameIsFixed": true,
  "overrideValues": [
    {
      "_class": "overrideValue",
      "do_objectID": "ABC14226-004C-469B-937E-AC69F14BAEF8",
      "overrideName": "32957303-A8DF-4C49-A1FB-7809C64EAB5D_symbolID",
      "value": "CBBD784F-CD33-4004-B83D-A3ED6A0E5ADB"
    }
  ],
  "resizingConstraint": 45,
  "resizingType": 0,
  "rotation": 0,
  "scale": 1,
  "shouldBreakMaskChain": false,
  "style": {
    "_class": "style",
    "contextSettings": {
      "_class": "graphicsContextSettings",
      "blendMode": 0,
      "do_objectID": "9ED38BF9-2542-4FF6-B5D1-4D4051D4B12F",
      "opacity": 0.3799999952316284
    },
    "do_objectID": "A6996DBE-05C3-4601-8F80-5CAE4D07A904",
    "endMarkerType": 0,
    "miterLimit": 10,
    "startMarkerType": 0,
    "windingRule": 1
  },
  "symbolID": "4845115C-B694-4297-8986-F9CBBF31CB58",
  "verticalSpacing": 0
}