{
  "_class": "symbolInstance",
  "booleanOperation": 0,
  "do_objectID": "A8FC142E-CA6C-470F-BCE0-987B408187B8",
  "exportOptions": {
    "_class": "exportOptions",
    "do_objectID": "BECDDBCA-D6A9-409A-B7E4-E8C72F86897D",
    "exportFormats": [
    ],
    "includedLayerIds": [
    ],
    "layerOptions": 0,
    "shouldTrim": false
  },
  "frame": {
    "_class": "rect",
    "constrainProportions": true,
    "do_objectID": "395B7A26-F6AD-4C47-A79B-A784A12BDC04",
    "height": 117,
    "width": 117,
    "x": 0,
    "y": 0
  },
  "horizontalSpacing": 0,
  "isFixedToViewport": false,
  "isFlippedHorizontal": false,
  "isFlippedVertical": false,
  "isLocked": false,
  "isVisible": true,
  "layerListExpandedType": 0,
  "name": "Color",
  "nameIsFixed": true,
  "overrideValues": [
    {
      "_class": "overrideValue",
      "do_objectID": "CFFFBABE-BAF3-4CED-AABB-EAEBF5BB82F7",
      "overrideName": "677A8015-2ADB-4217-A8A4-D335305F7967_symbolID",
      "value": "179520DE-3140-4B82-9165-696EABE0AE38"
    }
  ],
  "resizingConstraint": 63,
  "resizingType": 0,
  "rotation": 0,
  "scale": 1,
  "shouldBreakMaskChain": false,
  "style": {
    "_class": "style",
    "contextSettings": {
      "_class": "graphicsContextSettings",
      "blendMode": 0,
      "do_objectID": "2B564925-D8CF-4E2D-89BE-09970E8FFAE7",
      "opacity": 0.12
    },
    "do_objectID": "4B5EE8CF-423C-40DD-A528-54C2411D4FA1",
    "endMarkerType": 0,
    "miterLimit": 10,
    "startMarkerType": 0,
    "windingRule": 1
  },
  "symbolID": "179520DE-3140-4B82-9165-696EABE0AE38",
  "verticalSpacing": 0
}