{
  "_class": "symbolInstance",
  "booleanOperation": 0,
  "do_objectID": "2D4FE011-A7C5-4F52-B293-6D8618A59763",
  "exportOptions": {
    "_class": "exportOptions",
    "do_objectID": "2675733A-502C-42DF-A727-C1D9D6E6622E",
    "exportFormats": [
    ],
    "includedLayerIds": [
    ],
    "layerOptions": 0,
    "shouldTrim": false
  },
  "frame": {
    "_class": "rect",
    "constrainProportions": false,
    "do_objectID": "815872AE-A09D-4295-B743-C4676F395D13",
    "height": 24,
    "width": 40,
    "x": 269,
    "y": 954
  },
  "horizontalSpacing": 0,
  "isFixedToViewport": false,
  "isFlippedHorizontal": false,
  "isFlippedVertical": false,
  "isLocked": false,
  "isVisible": true,
  "layerListExpandedType": 0,
  "name": "Selection Control / Switch / On / Disabled",
  "nameIsFixed": false,
  "overrideValues": [
    {
      "_class": "overrideValue",
      "do_objectID": "53E5B43D-1DFD-48C9-9E50-674E99B60C0B",
      "overrideName": "5CAFCF56-0811-4B83-94D7-A5628A0EDCA1/340367BA-F69F-414A-80AE-D549677E2393_symbolID",
      "value": ""
    }
  ],
  "resizingConstraint": 63,
  "resizingType": 0,
  "rotation": 0,
  "scale": 1,
  "shouldBreakMaskChain": false,
  "style": {
    "_class": "style",
    "do_objectID": "DD6A0609-A3C3-48F8-8791-A9EC4038F392",
    "endMarkerType": 0,
    "miterLimit": 10,
    "startMarkerType": 0,
    "windingRule": 1
  },
  "symbolID": "95A96B61-3E97-4E1A-8398-27B425857103",
  "verticalSpacing": 0
}