{
  "_class": "symbolInstance",
  "booleanOperation": 0,
  "do_objectID": "E0CDA029-5A2D-442C-9562-3FE96581CFB8",
  "exportOptions": {
    "_class": "exportOptions",
    "do_objectID": "3FE494F3-AF91-48F2-9ACC-4F061841EC3D",
    "exportFormats": [
    ],
    "includedLayerIds": [
    ],
    "layerOptions": 0,
    "shouldTrim": false
  },
  "frame": {
    "_class": "rect",
    "constrainProportions": false,
    "do_objectID": "090E695F-E704-448F-B6DD-038BD9922D00",
    "height": 16,
    "width": 312,
    "x": 16,
    "y": 59
  },
  "horizontalSpacing": 0,
  "isFixedToViewport": false,
  "isFlippedHorizontal": false,
  "isFlippedVertical": false,
  "isLocked": false,
  "isVisible": true,
  "layerListExpandedType": 0,
  "name": "CAPTION TEXT COLOR & STYLE",
  "nameIsFixed": true,
  "overrideValues": [
    {
      "_class": "overrideValue",
      "do_objectID": "EE714310-03C1-4F17-A344-6E72DBE6DF3F",
      "overrideName": "46109C73-3E3E-4823-B32B-7ED5C14C77A7_stringValue",
      "value": "Assistive text"
    }
  ],
  "resizingConstraint": 10,
  "resizingType": 0,
  "rotation": 0,
  "scale": 1,
  "shouldBreakMaskChain": true,
  "style": {
    "_class": "style",
    "do_objectID": "6A981394-B4A9-44EC-A2E4-0D04BC7E75CA",
    "endMarkerType": 0,
    "miterLimit": 10,
    "startMarkerType": 0,
    "windingRule": 1
  },
  "symbolID": "3921FD3D-A55A-48F0-B626-ED02082A83E9",
  "verticalSpacing": 0
}