{
  "_class": "symbolInstance",
  "booleanOperation": 0,
  "do_objectID": "37AE7EB7-1C81-4CF8-98ED-C2222FDCEAF2",
  "exportOptions": {
    "_class": "exportOptions",
    "do_objectID": "88922219-F930-400C-865B-0194DCE58D4A",
    "exportFormats": [
    ],
    "includedLayerIds": [
    ],
    "layerOptions": 0,
    "shouldTrim": false
  },
  "frame": {
    "_class": "rect",
    "constrainProportions": false,
    "do_objectID": "7E0F11F7-1F0D-4F79-B113-C5236D927F45",
    "height": 24,
    "width": 272,
    "x": 72,
    "y": 82
  },
  "horizontalSpacing": 0,
  "isFixedToViewport": false,
  "isFlippedHorizontal": false,
  "isFlippedVertical": false,
  "isLocked": false,
  "isVisible": true,
  "layerListExpandedType": 0,
  "name": "HEADLINE 6 COLOR & STYLE",
  "nameIsFixed": true,
  "overrideValues": [
  ],
  "resizingConstraint": 43,
  "resizingType": 0,
  "rotation": 0,
  "scale": 1,
  "shouldBreakMaskChain": false,
  "style": {
    "_class": "style",
    "do_objectID": "619B3B41-B279-4403-9008-3477EE9DDAFC",
    "endMarkerType": 0,
    "miterLimit": 10,
    "startMarkerType": 0,
    "windingRule": 1
  },
  "symbolID": "414E568B-2DF1-4D7E-B6BD-29335EE978D5",
  "verticalSpacing": 0
}