{
  "_class": "shapePath",
  "booleanOperation": -1,
  "do_objectID": "33A3A4F2-4464-4FD5-8A31-11713E12EA01",
  "edited": true,
  "exportOptions": {
    "_class": "exportOptions",
    "exportFormats": [
    ],
    "includedLayerIds": [
    ],
    "layerOptions": 0,
    "shouldTrim": false
  },
  "frame": {
    "_class": "rect",
    "constrainProportions": false,
    "height": 9.149999999999999,
    "width": 6,
    "x": 0,
    "y": 0
  },
  "isClosed": true,
  "isFixedToViewport": false,
  "isFlippedHorizontal": false,
  "isFlippedVertical": false,
  "isLocked": false,
  "isVisible": true,
  "layerListExpandedType": 0,
  "name": "Path",
  "nameIsFixed": false,
  "pointRadiusBehaviour": 1,
  "points": [
    {
      "_class": "curvePoint",
      "cornerRadius": 0,
      "curveFrom": "{0.25, 0}",
      "curveMode": 1,
      "curveTo": "{0.25, 0}",
      "hasCurveFrom": false,
      "hasCurveTo": false,
      "point": "{0.25, 0}"
    },
    {
      "_class": "curvePoint",
      "cornerRadius": 0,
      "curveFrom": "{0, 0}",
      "curveMode": 1,
      "curveTo": "{0, 0}",
      "hasCurveFrom": false,
      "hasCurveTo": false,
      "point": "{0, 0}"
    },
    {
      "_class": "curvePoint",
      "cornerRadius": 0,
      "curveFrom": "{0, 0.65573770491803285}",
      "curveMode": 1,
      "curveTo": "{0, 0.65573770491803285}",
      "hasCurveFrom": false,
      "hasCurveTo": false,
      "point": "{0, 0.65573770491803285}"
    },
    {
      "_class": "curvePoint",
      "cornerRadius": 0,
      "curveFrom": "{0.875, 1}",
      "curveMode": 1,
      "curveTo": "{0.875, 1}",
      "hasCurveFrom": false,
      "hasCurveTo": false,
      "point": "{0.875, 1}"
    },
    {
      "_class": "curvePoint",
      "cornerRadius": 0,
      "curveFrom": "{1, 0.86557377049180317}",
      "curveMode": 1,
      "curveTo": "{1, 0.86557377049180317}",
      "hasCurveFrom": false,
      "hasCurveTo": false,
      "point": "{1, 0.86557377049180317}"
    },
    {
      "_class": "curvePoint",
      "cornerRadius": 0,
      "curveFrom": "{0.25, 0.57377049180327855}",
      "curveMode": 1,
      "curveTo": "{0.25, 0.57377049180327855}",
      "hasCurveFrom": false,
      "hasCurveTo": false,
      "point": "{0.25, 0.57377049180327855}"
    }
  ],
  "resizingConstraint": 63,
  "resizingType": 0,
  "rotation": 0,
  "shouldBreakMaskChain": false
}