{
  "_class": "symbolInstance",
  "booleanOperation": 0,
  "do_objectID": "68EDAAB4-7FBF-4413-A579-BBA3DD7B9327",
  "exportOptions": {
    "_class": "exportOptions",
    "do_objectID": "768B8A5D-1AF1-42DD-8C42-70DB0FA822B4",
    "exportFormats": [
    ],
    "includedLayerIds": [
    ],
    "layerOptions": 0,
    "shouldTrim": false
  },
  "frame": {
    "_class": "rect",
    "constrainProportions": false,
    "do_objectID": "1BA74877-06DC-4B65-8BF4-8B6DC244D074",
    "height": 16,
    "width": 64,
    "x": 16,
    "y": 10
  },
  "horizontalSpacing": 0,
  "isFixedToViewport": false,
  "isFlippedHorizontal": false,
  "isFlippedVertical": false,
  "isLocked": false,
  "isVisible": true,
  "layerListExpandedType": 0,
  "name": "TEXT COLOR & STYLE",
  "nameIsFixed": true,
  "overrideValues": [
  ],
  "resizingConstraint": 42,
  "resizingType": 0,
  "rotation": 0,
  "scale": 1,
  "shouldBreakMaskChain": false,
  "style": {
    "_class": "style",
    "do_objectID": "F9B0B1A8-4B97-4CF2-BF64-6293880A3495",
    "endMarkerType": 0,
    "miterLimit": 10,
    "startMarkerType": 0,
    "windingRule": 1
  },
  "symbolID": "8095A6A2-9C98-43D7-9634-B80A2F6ED29D",
  "verticalSpacing": 0
}