{
  "_class": "symbolInstance",
  "booleanOperation": 0,
  "do_objectID": "36E3FB58-0D8E-4A2F-B88E-1FBF039043EA",
  "exportOptions": {
    "_class": "exportOptions",
    "do_objectID": "24645C64-FC95-49A5-94C6-BFFA34B2E876",
    "exportFormats": [
    ],
    "includedLayerIds": [
    ],
    "layerOptions": 0,
    "shouldTrim": false
  },
  "frame": {
    "_class": "rect",
    "constrainProportions": false,
    "do_objectID": "7727E713-15D3-4410-BD24-81CA65EB0D6F",
    "height": 20,
    "width": 312,
    "x": 16,
    "y": 375
  },
  "horizontalSpacing": 0,
  "isFixedToViewport": false,
  "isFlippedHorizontal": false,
  "isFlippedVertical": false,
  "isLocked": false,
  "isVisible": true,
  "layerListExpandedType": 0,
  "name": "SUBTITLE 1 COLOR & STYLE",
  "nameIsFixed": true,
  "overrideValues": [
    {
      "_class": "overrideValue",
      "do_objectID": "CEC04344-3B19-41B1-A107-D095255439F2",
      "overrideName": "47EDEAB5-B6AE-44AF-B6C9-197F450AE9B7_stringValue",
      "value": "Subtitle"
    }
  ],
  "resizingConstraint": 58,
  "resizingType": 0,
  "rotation": 0,
  "scale": 1,
  "shouldBreakMaskChain": false,
  "style": {
    "_class": "style",
    "do_objectID": "DBB7C354-2F16-47C7-A3E7-CA28E8B46EB2",
    "endMarkerType": 0,
    "miterLimit": 10,
    "startMarkerType": 0,
    "windingRule": 1
  },
  "symbolID": "71D4D49D-D7E7-43A0-B568-FC6D006AD448",
  "verticalSpacing": 0
}