{
  "_class": "symbolMaster",
  "backgroundColor": {
    "_class": "color",
    "alpha": 1,
    "blue": 1,
    "do_objectID": "59C2F4C8-C8EC-400B-B49C-56EB046F7775",
    "green": 1,
    "red": 1
  },
  "booleanOperation": 0,
  "changeIdentifier": 2092,
  "do_objectID": "F23A01A7-FEBD-4CFB-AC6B-02CF0294AECC",
  "exportOptions": {
    "_class": "exportOptions",
    "do_objectID": "68D7BECD-AAF5-49CA-8066-F1D9BF68883C",
    "exportFormats": [
    ],
    "includedLayerIds": [
    ],
    "layerOptions": 0,
    "shouldTrim": false
  },
  "frame": {
    "_class": "rect",
    "constrainProportions": false,
    "do_objectID": "836AA022-FE2B-4634-B6D4-6B18C914797E",
    "height": 16,
    "width": 45,
    "x": 102908,
    "y": 56
  },
  "grid": {
    "_class": "simpleGrid",
    "gridSize": 4,
    "isEnabled": true,
    "thickGridTimes": 40
  },
  "hasBackgroundColor": false,
  "hasClickThrough": true,
  "horizontalRulerData": {
    "_class": "rulerData",
    "base": 0,
    "do_objectID": "553A8C18-F573-4204-907F-89CDB860479E",
    "guides": [
    ]
  },
  "includeBackgroundColorInExport": true,
  "includeBackgroundColorInInstance": false,
  "includeInCloudUpload": true,
  "isFixedToViewport": false,
  "isFlippedHorizontal": false,
  "isFlippedVertical": false,
  "isFlowHome": false,
  "isLocked": false,
  "isVisible": true,
  "layerListExpandedType": 1,
  "layers": [
    {
      "class": "text",
      "id": "28A8D586-914A-48F2-9EF6-0056AD317E5B"
    }
  ],
  "layout": {
    "_class": "layoutGrid",
    "columnWidth": 48,
    "drawHorizontal": true,
    "drawHorizontalLines": false,
    "drawVertical": false,
    "gutterHeight": 4,
    "gutterWidth": 2904,
    "guttersOutside": false,
    "horizontalOffset": -123,
    "isEnabled": false,
    "numberOfColumns": 2,
    "rowHeightMultiplication": 1,
    "totalWidth": 3000
  },
  "name": "✱ / Text / Caption / Selected / On Surface / High Emphasis / Left",
  "nameIsFixed": true,
  "resizesContent": true,
  "resizingConstraint": 63,
  "resizingType": 0,
  "rotation": 0,
  "shouldBreakMaskChain": true,
  "style": {
    "_class": "style",
    "do_objectID": "7B541BBF-8E7F-477F-A22D-D6D4870E480B",
    "endMarkerType": 0,
    "miterLimit": 10,
    "startMarkerType": 0,
    "windingRule": 1
  },
  "symbolID": "C6621AD4-2069-4582-B682-31B80AEE2BDD",
  "verticalRulerData": {
    "_class": "rulerData",
    "base": 0,
    "do_objectID": "6667E109-109B-414C-A18F-F06D9EA210FD",
    "guides": [
    ]
  }
}