{
  "_class": "symbolInstance",
  "booleanOperation": 0,
  "do_objectID": "0A393119-65FC-468C-8CF9-A40B88C76DF8",
  "exportOptions": {
    "_class": "exportOptions",
    "do_objectID": "D98DCC8B-E575-4CEE-A8F1-877232C3D45E",
    "exportFormats": [
    ],
    "includedLayerIds": [
    ],
    "layerOptions": 0,
    "shouldTrim": false
  },
  "frame": {
    "_class": "rect",
    "constrainProportions": false,
    "do_objectID": "FF6B943C-D1C3-47AA-A44A-70AB019A2501",
    "height": 24,
    "width": 24,
    "x": 332,
    "y": 1392
  },
  "horizontalSpacing": 0,
  "isFixedToViewport": false,
  "isFlippedHorizontal": false,
  "isFlippedVertical": false,
  "isLocked": false,
  "isVisible": true,
  "layerListExpandedType": 0,
  "name": "Icon / Visibility / Filled",
  "nameIsFixed": false,
  "overrideValues": [
    {
      "_class": "overrideValue",
      "overrideName": "B7317943-8AFB-4E19-9A32-F471039F5809_symbolID",
      "value": "CED0B635-AFB1-4801-AE71-072DC190EC48"
    }
  ],
  "resizingConstraint": 45,
  "resizingType": 0,
  "rotation": 0,
  "scale": 1,
  "shouldBreakMaskChain": false,
  "style": {
    "_class": "style",
    "do_objectID": "FAEEA5A2-B5A4-49D2-8445-4B31CC796679",
    "endMarkerType": 0,
    "miterLimit": 10,
    "startMarkerType": 0,
    "windingRule": 1
  },
  "symbolID": "74AF142B-4FF0-4220-B3CF-6B3999E91506",
  "verticalSpacing": 0
}