{
  "_class": "symbolInstance",
  "booleanOperation": 0,
  "do_objectID": "47C0ED03-BBA6-46AB-A3EA-FE01C42AB95D",
  "exportOptions": {
    "_class": "exportOptions",
    "do_objectID": "75704E2C-472C-4A61-9437-2FE3D6FC8555",
    "exportFormats": [
    ],
    "includedLayerIds": [
    ],
    "layerOptions": 0,
    "shouldTrim": false
  },
  "frame": {
    "_class": "rect",
    "constrainProportions": false,
    "do_objectID": "D5815AE5-F33A-4E4B-88F0-345C1AF0BC4C",
    "height": 24,
    "width": 24,
    "x": 636,
    "y": 2108
  },
  "horizontalSpacing": 0,
  "isFixedToViewport": false,
  "isFlippedHorizontal": false,
  "isFlippedVertical": false,
  "isLocked": false,
  "isVisible": true,
  "layerListExpandedType": 0,
  "name": "Icon / Flight Land / Two-toned",
  "nameIsFixed": false,
  "overrideValues": [
  ],
  "resizingConstraint": 45,
  "resizingType": 0,
  "rotation": 0,
  "scale": 1,
  "shouldBreakMaskChain": false,
  "style": {
    "_class": "style",
    "do_objectID": "F24F9159-7123-422B-90CD-CE6C8ED6B96E",
    "endMarkerType": 0,
    "miterLimit": 10,
    "startMarkerType": 0,
    "windingRule": 1
  },
  "symbolID": "960F3F44-6D11-427B-A313-0BDF55F54C87",
  "verticalSpacing": 0
}