{
  "_class": "symbolInstance",
  "booleanOperation": 0,
  "do_objectID": "D7A11C13-6558-4309-914E-8F99B02D6D08",
  "exportOptions": {
    "_class": "exportOptions",
    "do_objectID": "C8883510-573D-427B-B892-B78543C5A389",
    "exportFormats": [
    ],
    "includedLayerIds": [
    ],
    "layerOptions": 0,
    "shouldTrim": false
  },
  "frame": {
    "_class": "rect",
    "constrainProportions": false,
    "do_objectID": "B7A6EB4C-39C0-48AE-BDBD-6FCEA630DD56",
    "height": 24,
    "width": 24,
    "x": 860,
    "y": 1584
  },
  "horizontalSpacing": 0,
  "isFixedToViewport": false,
  "isFlippedHorizontal": false,
  "isFlippedVertical": false,
  "isLocked": false,
  "isVisible": true,
  "layerListExpandedType": 0,
  "name": "Icon / Fullscreen / Sharp",
  "nameIsFixed": false,
  "overrideValues": [
    {
      "_class": "overrideValue",
      "do_objectID": "79668B6F-64B7-4471-9401-7B6D44A7E1C0",
      "overrideName": "4C9304F9-9540-4838-847B-9FDF2815C487_symbolID",
      "value": "CED0B635-AFB1-4801-AE71-072DC190EC48"
    }
  ],
  "resizingConstraint": 45,
  "resizingType": 0,
  "rotation": 0,
  "scale": 1,
  "shouldBreakMaskChain": false,
  "style": {
    "_class": "style",
    "do_objectID": "8D8580AE-413E-4A1A-AE83-EEAB4C9621A7",
    "endMarkerType": 0,
    "miterLimit": 10,
    "startMarkerType": 0,
    "windingRule": 1
  },
  "symbolID": "BD1568A8-3E7D-48BC-8E6F-C771505A2409",
  "verticalSpacing": 0
}