{
  "_class": "shapeGroup",
  "booleanOperation": 0,
  "clippingMaskMode": 0,
  "do_objectID": "4A59D1A8-6AF0-4A7A-838F-5D0880850FC6",
  "exportOptions": {
    "_class": "exportOptions",
    "do_objectID": "DC8F9A67-AE4E-40F0-8CE1-0909F7AD82E2",
    "exportFormats": [
    ],
    "includedLayerIds": [
    ],
    "layerOptions": 0,
    "shouldTrim": false
  },
  "frame": {
    "_class": "rect",
    "constrainProportions": false,
    "do_objectID": "9B633401-2291-4234-B325-EFE03E71816A",
    "height": 3,
    "width": 10,
    "x": 0.9284999999999997,
    "y": 13
  },
  "hasClickThrough": false,
  "hasClippingMask": false,
  "isFixedToViewport": false,
  "isFlippedHorizontal": false,
  "isFlippedVertical": false,
  "isLocked": false,
  "isVisible": true,
  "layerListExpandedType": 0,
  "layers": [
    {
      "class": "shapePath",
      "id": "CBB949E0-7A33-4BCB-B1D8-DAE1D7257EC1"
    },
    {
      "class": "shapePath",
      "id": "67D9962A-3833-49DC-884D-6A290BBC8625"
    }
  ],
  "name": "Fill 12",
  "nameIsFixed": false,
  "resizingConstraint": 63,
  "resizingType": 0,
  "rotation": 0,
  "shouldBreakMaskChain": false,
  "style": {
    "_class": "style",
    "do_objectID": "856DAAE8-EBF4-4825-B05C-30287F23D2FA",
    "endMarkerType": 0,
    "fills": [
      {
        "_class": "fill",
        "color": {
          "_class": "color",
          "alpha": 1,
          "blue": 0,
          "green": 0,
          "red": 0
        },
        "fillType": 0,
        "isEnabled": true,
        "noiseIndex": 0,
        "noiseIntensity": 0,
        "patternFillType": 1,
        "patternTileScale": 1
      }
    ],
    "miterLimit": 10,
    "startMarkerType": 0,
    "windingRule": 1
  },
  "windingRule": 1
}