{
  "_class": "symbolInstance",
  "booleanOperation": -1,
  "clippingMaskMode": 0,
  "do_objectID": "C8271B76-EB3B-47A9-ADAF-E1357456E64F",
  "exportOptions": {
    "_class": "exportOptions",
    "do_objectID": "72AB2C17-D5D6-44DC-83F7-638B4491D251",
    "exportFormats": [
    ],
    "includedLayerIds": [
    ],
    "layerOptions": 0,
    "shouldTrim": false
  },
  "frame": {
    "_class": "rect",
    "constrainProportions": false,
    "do_objectID": "1425A7AD-3E14-4AAC-AF16-1BD3297A8566",
    "height": 947,
    "width": 244,
    "x": 0,
    "y": 97
  },
  "hasClippingMask": false,
  "horizontalSpacing": 0,
  "isFixedToViewport": false,
  "isFlippedHorizontal": false,
  "isFlippedVertical": false,
  "isLocked": false,
  "isVisible": true,
  "layerListExpandedType": 0,
  "name": "✱ / Color / Surface / Main",
  "nameIsFixed": false,
  "overrideValues": [
  ],
  "resizingConstraint": 63,
  "resizingType": 0,
  "rotation": 0,
  "scale": 1,
  "shouldBreakMaskChain": false,
  "style": {
    "_class": "style",
    "do_objectID": "608AED9E-B702-47E7-A950-967FCFA8DE3E",
    "endMarkerType": 0,
    "miterLimit": 10,
    "startMarkerType": 0,
    "windingRule": 1
  },
  "symbolID": "EF84EC56-5A77-45C8-BDC4-076197D51D6D",
  "verticalSpacing": 0
}