{
  "_class": "group",
  "booleanOperation": 0,
  "do_objectID": "33EB8598-A562-4042-A0E5-2F5BB7D27D75",
  "exportOptions": {
    "_class": "exportOptions",
    "exportFormats": [
    ],
    "includedLayerIds": [
    ],
    "layerOptions": 0,
    "shouldTrim": false
  },
  "frame": {
    "_class": "rect",
    "constrainProportions": false,
    "height": 20,
    "width": 815,
    "x": 88,
    "y": 367
  },
  "hasClickThrough": false,
  "isFixedToViewport": false,
  "isFlippedHorizontal": false,
  "isFlippedVertical": false,
  "isLocked": true,
  "isVisible": true,
  "layerListExpandedType": 0,
  "layers": [
    {
      "class": "symbolInstance",
      "id": "04E47F75-F53C-47E7-BE43-22B233125A07"
    },
    {
      "class": "symbolInstance",
      "id": "341F9E86-3A8E-420E-A6F8-E6767075DFB8"
    },
    {
      "class": "symbolInstance",
      "id": "53191BC6-A072-4A88-AAE5-53CA8EED9A27"
    },
    {
      "class": "symbolInstance",
      "id": "F5ED8F4D-2B94-4699-ADD1-5CC048988138"
    },
    {
      "class": "symbolInstance",
      "id": "B9C18CDB-A7EA-4643-8597-DD27412A563B"
    },
    {
      "class": "symbolInstance",
      "id": "AE61599B-B402-4807-9608-13E4CA2DB14A"
    }
  ],
  "name": "Captions",
  "nameIsFixed": true,
  "resizingConstraint": 63,
  "resizingType": 0,
  "rotation": 0,
  "shouldBreakMaskChain": false,
  "style": {
    "_class": "style",
    "endMarkerType": 0,
    "miterLimit": 10,
    "startMarkerType": 0,
    "windingRule": 1
  }
}