{
  "_class": "symbolInstance",
  "booleanOperation": 0,
  "do_objectID": "66FDCF19-E729-49BE-B4C6-7BEFD3EB7013",
  "exportOptions": {
    "_class": "exportOptions",
    "do_objectID": "B03D5C41-9461-4EC4-9A11-9F949733D178",
    "exportFormats": [
    ],
    "includedLayerIds": [
    ],
    "layerOptions": 0,
    "shouldTrim": false
  },
  "frame": {
    "_class": "rect",
    "constrainProportions": false,
    "do_objectID": "66FB7787-75C2-472C-BDF1-811BD5A86453",
    "height": 640,
    "width": 360,
    "x": 500,
    "y": 149
  },
  "horizontalSpacing": 0,
  "isFixedToViewport": false,
  "isFlippedHorizontal": false,
  "isFlippedVertical": false,
  "isLocked": false,
  "isVisible": true,
  "layerListExpandedType": 0,
  "name": "Navigation Drawer / Side / Resting",
  "nameIsFixed": false,
  "overrideValues": [
  ],
  "resizingConstraint": 63,
  "resizingType": 0,
  "rotation": 0,
  "scale": 1,
  "shouldBreakMaskChain": false,
  "style": {
    "_class": "style",
    "do_objectID": "18F8EFB9-EFBA-4E28-8407-45A46023269C",
    "endMarkerType": 0,
    "miterLimit": 10,
    "startMarkerType": 0,
    "windingRule": 1
  },
  "symbolID": "52552AAD-F290-4D49-9130-FA9FDFE00952",
  "verticalSpacing": 0
}