{
  "_class": "symbolInstance",
  "booleanOperation": 0,
  "do_objectID": "7453487C-155D-45FB-B757-A47635469F74",
  "exportOptions": {
    "_class": "exportOptions",
    "do_objectID": "7903C400-CF84-4B39-9FA6-1666893E9606",
    "exportFormats": [
    ],
    "includedLayerIds": [
    ],
    "layerOptions": 0,
    "shouldTrim": false
  },
  "frame": {
    "_class": "rect",
    "constrainProportions": false,
    "do_objectID": "52AE84CA-97EB-481B-88E9-665EDF905664",
    "height": 472,
    "width": 344,
    "x": 0,
    "y": 0
  },
  "horizontalSpacing": 0,
  "isFixedToViewport": false,
  "isFlippedHorizontal": false,
  "isFlippedVertical": false,
  "isLocked": false,
  "isVisible": true,
  "layerListExpandedType": 0,
  "name": "CONTAINER COLOR",
  "nameIsFixed": true,
  "overrideValues": [
  ],
  "resizingConstraint": 63,
  "resizingType": 0,
  "rotation": 0,
  "scale": 1,
  "shouldBreakMaskChain": false,
  "style": {
    "_class": "style",
    "do_objectID": "178682A3-731A-4152-A663-3518B4911248",
    "endMarkerType": 0,
    "miterLimit": 10,
    "startMarkerType": 0,
    "windingRule": 1
  },
  "symbolID": "13A98AD8-2C72-4ED5-B872-A1CDF9769942",
  "verticalSpacing": 0
}