{
  "_class": "symbolInstance",
  "booleanOperation": 0,
  "do_objectID": "CC0AA89E-DEFC-4678-BE9D-4F7AE668C154",
  "exportOptions": {
    "_class": "exportOptions",
    "do_objectID": "EBD2CA05-0B8C-4489-8BD3-FAEB234F1E55",
    "exportFormats": [
    ],
    "includedLayerIds": [
    ],
    "layerOptions": 0,
    "shouldTrim": false
  },
  "frame": {
    "_class": "rect",
    "constrainProportions": false,
    "do_objectID": "083446B7-84CF-4206-B9CF-3DAD8D1B3294",
    "height": 28,
    "width": 509,
    "x": 164,
    "y": 344
  },
  "horizontalSpacing": 0,
  "isFixedToViewport": false,
  "isFlippedHorizontal": false,
  "isFlippedVertical": false,
  "isLocked": true,
  "isVisible": true,
  "layerListExpandedType": 0,
  "name": "✱ / Text / Body 1 / Black / High Emphasis / Left",
  "nameIsFixed": true,
  "overrideValues": [
    {
      "_class": "overrideValue",
      "do_objectID": "33A03101-3C82-4DE7-B189-292394868ED2",
      "overrideName": "73766BB3-BE0F-43B4-9887-148CB9C8FF1B_stringValue",
      "value": "Surface"
    }
  ],
  "resizingConstraint": 63,
  "resizingType": 0,
  "rotation": 0,
  "scale": 1,
  "shouldBreakMaskChain": true,
  "style": {
    "_class": "style",
    "do_objectID": "853606C4-4C86-4BA7-ACB8-6A226EA106B7",
    "endMarkerType": 0,
    "miterLimit": 10,
    "startMarkerType": 0,
    "windingRule": 1
  },
  "symbolID": "BCBF0513-966C-4C9F-96B5-58F602B90938",
  "verticalSpacing": 0
}