{
  "_class": "symbolInstance",
  "booleanOperation": 0,
  "do_objectID": "25112376-2DC2-40F4-A8F0-A60FAAA07055",
  "exportOptions": {
    "_class": "exportOptions",
    "do_objectID": "9B32B2D9-E1DF-4784-B3DE-A793E87FF7A7",
    "exportFormats": [
    ],
    "includedLayerIds": [
    ],
    "layerOptions": 0,
    "shouldTrim": false
  },
  "frame": {
    "_class": "rect",
    "constrainProportions": false,
    "do_objectID": "CC358ED2-4C48-4562-8E3A-100ADA915AFC",
    "height": 40,
    "width": 304,
    "x": 80,
    "y": 644
  },
  "horizontalSpacing": 0,
  "isFixedToViewport": false,
  "isFlippedHorizontal": false,
  "isFlippedVertical": false,
  "isLocked": false,
  "isVisible": true,
  "layerListExpandedType": 0,
  "name": "Cards / Elements / Title Block / Image",
  "nameIsFixed": false,
  "overrideValues": [
  ],
  "resizingConstraint": 63,
  "resizingType": 0,
  "rotation": 0,
  "scale": 1,
  "shouldBreakMaskChain": false,
  "style": {
    "_class": "style",
    "do_objectID": "8FAF5843-C068-4D22-8E1F-22CDF50DB59C",
    "endMarkerType": 0,
    "miterLimit": 10,
    "startMarkerType": 0,
    "windingRule": 1
  },
  "symbolID": "142555A7-8D28-44C6-9E9A-B748D43B13C8",
  "verticalSpacing": 0
}